{
  "meta": {
    "cssMode": "atomic",
    "description": "A community for people who build design systems to share and learn from each other.",
    "engine": "x0",
    "favicon": "assets/favicon.png",
    "icon": "assets/apple-touch-icon.png",
    "image": "http://designsystems.nyc/assets/apple-touch-icon.png",
    "letter": "A",
    "title": "Design Systems Coalition NYC",
    "twitterSite": "@nyc_dsc",
    "version": "0.0.45",
    "xicon": {
      "backgroundColor": 3,
      "color": 0,
      "fontFamily": "\"Helvetica Neue\", Helvetica, Arial, sans-serif",
      "fontSize": 32,
      "letter": "DS"
    }
  },
  "content": [
    {
      "_id": 1,
      "heading": "Design Systems Coalition",
      "links": [],
      "meta": {
        "colors": {
          "background": 3,
          "button": {},
          "text": 0
        },
        "layout": {
          "paddingBottom": [
            5
          ]
        },
        "name": "Bold",
        "type": "header"
      },
      "styles": {},
      "subhead": "NYC",
      "text": "A community for people who build design systems to share and learn from each other."
    },
    {
      "_id": 291964490058876,
      "embed": "",
      "heading": "Empowering product growth with design systems",
      "image": "",
      "kicker": "",
      "links": [
        {
          "_id": 291964490060654,
          "href": "https://www.meetup.com/NYC-Design-Systems-Coalition/events/241892347/",
          "icon": "",
          "text": "RSVP",
          "type": 2
        }
      ],
      "meta": {
        "colors": {
          "background": "white",
          "button": {}
        },
        "layout": {
          "paddingTop": [
            5
          ]
        },
        "name": "SplitRight_1_4",
        "type": "section",
        "typography": {
          "h1": null
        }
      },
      "subhead": "Aug 17 @ DoSomething",
      "text": ""
    },
    {
      "_id": 291964490057952,
      "items": [
        {
          "_id": 291964490057964,
          "heading": "Jina Anne",
          "href": "https://twitter.com/jina",
          "image": "https://user-images.githubusercontent.com/334891/28708396-fb712e8c-7330-11e7-9501-dd36c56aef70.png",
          "subhead": "",
          "text": "Jina is a consultant, community builder, and advocate focused on design systems.  She organizes Clarity, the first Design Systems conference. She founded the San Francisco Design Systems Coaltion (which now has chapters in New York and London). She created and moderates the Design Systems Slack. She maintains the design and website for Sass. She organizes The Mixin (a Sass and front end meet up). She also curates Sass News. At Salesforce, Jina was lead designer on the Lightning Design System."
        },
        {
          "_id": 291964490057963,
          "cta": "",
          "heading": "Una Kravets",
          "href": "https://twitter.com/una",
          "image": "https://user-images.githubusercontent.com/334891/28708358-d6dd8c1e-7330-11e7-8404-b7942a8c93fc.png",
          "kicker": "",
          "subhead": "",
          "text": "Una Kravets is a technical writer, open source advocate, and UI Engineer building the design system at DigitalOcean. She’s written for various online publications such as A List Apart, Smashing Magazine, and Sitepoint. Una also co-hosts the Toolsday podcast and started both the DC and Austin Sass Meetups. She’s a performance nerd and listens to way too many audio books."
        },
        {
          "_id": 291964490057965,
          "heading": "Luke Patton",
          "href": "https://twitter.com/friendofpixels",
          "image": "https://user-images.githubusercontent.com/334891/28708431-1ad4815c-7331-11e7-974c-4466b4361bc3.jpg",
          "kicker": "",
          "subhead": "",
          "text": "Luke Patton is a product designer building flexible technology and trying to bring human touches to large systems. At DoSomething.org, he helps build digital products and features to encourage social action. Luke spends his free time maintaining a healthy selection of side projects and volunteering with civic tech initiatives. He is a proud cat-dad, avid game player, and sci-fi nerd."
        }
      ],
      "meta": {
        "colors": {
          "background": "white",
          "button": {}
        },
        "layout": {
          "columns": [
            1,
            2,
            3,
            3
          ],
          "paddingBottom": [
            5
          ],
          "paddingTop": [
            3
          ]
        },
        "name": "Basic",
        "ratio": 0.5625,
        "type": "cards"
      },
      "subhead": "Speakers"
    },
    {
      "_id": 291964490058888,
      "embed": "",
      "heading": "Interview with Emily Brick",
      "image": "https://cdn-images-1.medium.com/max/1600/1*xb8yNsFWvDAGKp0f-WWiJw.jpeg",
      "kicker": "",
      "links": [
        {
          "_id": 291964490060241,
          "href": "https://medium.com/design-systems-nyc/interview-with-emily-brick-cce8a776a006",
          "icon": {},
          "text": "Read on Medium",
          "type": 3
        }
      ],
      "meta": {
        "colors": {
          "background": 0,
          "button": {},
          "text": "white"
        },
        "name": "Split",
        "type": "section",
        "typography": {
          "text": [
            2
          ]
        }
      },
      "subhead": "",
      "text": "Senior Product Designer at Buzzfeed, where she focuses on the site experience and their CSS framework, Solid."
    },
    {
      "_id": 291964490060645,
      "heading": "Previous meetups",
      "kicker": "",
      "meta": {
        "colors": {
          "background": "white",
          "button": {}
        },
        "layout": {
          "paddingBottom": [
            3
          ],
          "paddingTop": [
            5
          ]
        },
        "name": "Basic",
        "type": "header"
      },
      "text": ""
    },
    {
      "_id": 291964490061083,
      "heading": "Documenting design systems",
      "image": "assets/may-speaker-photo2.jpg",
      "links": [
        {
          "_id": 291964490063340,
          "href": "/2017-may",
          "icon": "",
          "text": "View photos & videos",
          "type": 4
        }
      ],
      "meta": {
        "layout": {
          "paddingBottom": [
            4
          ],
          "paddingTop": [
            4
          ]
        },
        "name": "Split_2_5",
        "ratio": 0.6,
        "type": "section",
        "typography": {
          "h1": [
            5
          ]
        }
      },
      "subhead": "May 11 @ Justworks",
      "text": "Featuring talks by Tom Takigayama from Justworks, Adekunle Oduye from Nasdaq, and Amélie Lamont from The New York Times."
    },
    {
      "_id": 5,
      "embed": "",
      "heading": "Brand design systems that scale",
      "image": "assets/DSC-02Etsy-4469.jpg",
      "links": [
        {
          "_id": 291964490050148,
          "href": "/2017-march",
          "icon": "",
          "text": "View photos & videos",
          "type": 4
        }
      ],
      "meta": {
        "colors": {
          "background": "white",
          "button": {
            "background": 0,
            "text": 3
          },
          "heading": 0,
          "kicker": 0,
          "link": null,
          "subhead": 3,
          "text": 0
        },
        "id": "march-meetup",
        "layout": {
          "paddingBottom": [
            4
          ],
          "paddingTop": [
            4
          ]
        },
        "name": "Split_2_5",
        "ratio": 0.6,
        "type": "section",
        "typography": {
          "h1": [
            5
          ]
        }
      },
      "styles": {},
      "subhead": "March 23 @ Etsy HQ",
      "text": "Featuring talks by Sophie Shepherd from GitHub, Will Miner from 2U, and Marco Suarez from Etsy."
    },
    {
      "_id": 7,
      "buttons": [
        {
          "_id": 8,
          "href": "https://www.youtube.com/watch?v=YSpQiestvjk",
          "text": "Watch on YouTube"
        },
        {
          "_id": 9,
          "href": "https://speakerdeck.com/emilybrick/solid-design-systems-lightning-talk",
          "text": "Solid"
        },
        {
          "_id": 10,
          "href": "https://speakerdeck.com/silviatc/nydsc-meetup-dec-2016-union-the-knots-new-design-system",
          "text": "Union"
        },
        {
          "_id": 11,
          "href": "https://speakerdeck.com/broccolini/building-design-systems-at-github",
          "text": "Primer"
        }
      ],
      "embed": "",
      "heading": "Sharing design systems journeys",
      "image": "assets/video-thumbnail.jpg",
      "links": [
        {
          "_id": 291964490060835,
          "href": "/2016-december",
          "icon": "",
          "text": "View video & slides",
          "type": 4
        }
      ],
      "meta": {
        "backgroundImage": "",
        "colors": {
          "background": "white",
          "button": {},
          "text": 0
        },
        "id": "december-meetup",
        "layout": {
          "paddingBottom": [
            5
          ],
          "paddingTop": [
            4
          ]
        },
        "name": "Split_2_5",
        "ratio": 0,
        "type": "section",
        "typography": {
          "h1": [
            5
          ]
        }
      },
      "styles": {},
      "subhead": "December 15 @ XO Group",
      "text": "Featuring Emily Brick from Buzzfeed, Silvia Tueros-Cossio and Philip Kelly from XO Group, and Diana Mounter from GitHub."
    },
    {
      "_id": 291964490050080,
      "buttons": [
        {
          "_id": 1304866528529473000,
          "href": "https://github.com/design-systems-coalition-NYC/meetup/issues/new",
          "text": "Get involved"
        }
      ],
      "heading": "Host or speak at our next meetup!",
      "image": "",
      "kicker": "",
      "links": [
        {
          "_id": 39123241666723656,
          "href": "https://github.com/design-systems-coalition-NYC/meetup/blob/master/README.md#how-to-get-involved-with-our-meetup",
          "icon": "",
          "text": "Get involved",
          "type": 2
        }
      ],
      "meta": {
        "backgroundImage": "assets/join-us-bg-4.jpg",
        "colors": {
          "background": "white",
          "button": {
            "background": 3,
            "text": 0
          },
          "heading": "white",
          "link": "white",
          "subhead": "white",
          "text": "white"
        },
        "layout": {
          "paddingBottom": [
            6
          ],
          "paddingTop": [
            6
          ]
        },
        "name": "Staggered",
        "ratio": 0,
        "type": "section"
      },
      "styles": {},
      "subhead": "",
      "text": "If you'd like to host a future meetup, are interested in speaking, or have ideas for topics you'd like to see covered, we'd love to hear from you."
    },
    {
      "_id": 16,
      "buttons": [
        {
          "_id": 17,
          "href": "https://twitter.com/tomtaki",
          "text": "Tom Takigayama"
        },
        {
          "_id": 18,
          "href": "https://twitter.com/broccolini",
          "text": "Diana Mounter"
        }
      ],
      "heading": "",
      "items": [
        {
          "_id": 19,
          "heading": "Diana Mounter",
          "image": "https://pbs.twimg.com/profile_images/412413402749743107/jOnza-Eg_400x400.jpeg",
          "links": "",
          "subhead": "",
          "text": "Design Systems Lead at GitHub"
        },
        {
          "_id": 20,
          "heading": "Tom Takigayama",
          "image": "https://pbs.twimg.com/profile_images/746829844026114049/N-gpR7I4_400x400.jpg",
          "links": "",
          "subhead": "",
          "text": "Product Design Lead at Justworks"
        }
      ],
      "meta": {
        "colors": {
          "background": 2,
          "button": {},
          "text": "white"
        },
        "layout": {
          "columns": [
            1,
            2
          ],
          "paddingBottom": [
            4
          ],
          "paddingTop": [
            5
          ]
        },
        "name": "Basic",
        "type": "profiles",
        "typography": {
          "h1": [
            3
          ]
        }
      },
      "styles": {},
      "subhead": "Organizers",
      "text": ""
    },
    {
      "_id": 21,
      "cta": [
        {
          "_id": 415089277328390000000,
          "href": "http://designsystems.herokuapp.com/",
          "text": "Slack"
        }
      ],
      "iconLinks": [
        {
          "_id": 2.6744482064160775e+28,
          "href": "",
          "icon": "twitter",
          "text": "Hello"
        },
        {
          "_id": 4.0116723096241574e+29,
          "href": "",
          "icon": "medium",
          "text": "Hello"
        },
        {
          "_id": 5.964019500307916e+30,
          "href": "",
          "icon": "github",
          "text": "Hello"
        }
      ],
      "links": [
        {
          "_id": 23,
          "href": "https://twitter.com/nyc_dsc",
          "text": "Twitter"
        },
        {
          "_id": 415088109470429800000,
          "href": "https://medium.com/design-systems-nyc",
          "icon": "",
          "text": "Medium"
        },
        {
          "_id": 24,
          "href": "https://github.com/design-systems-coalition-NYC/meetup",
          "text": "GitHub"
        },
        {
          "_id": 291964490050097,
          "type": "separator"
        },
        {
          "_id": 291964490050107,
          "href": "https://www.meetup.com/NYC-Design-Systems-Coalition/",
          "text": "Join us on Meetup",
          "type": 2
        }
      ],
      "meta": {
        "colors": {
          "background": 0,
          "button": {},
          "text": 3
        },
        "layout": {
          "paddingBottom": [
            4
          ],
          "paddingTop": [
            4
          ]
        },
        "name": "Basic",
        "type": "footer"
      },
      "small": "",
      "styles": {},
      "text": ""
    },
    {
      "_id": 291964490050085,
      "meta": {
        "colors": {
          "background": 2,
          "button": {},
          "text": 0
        },
        "name": "PromoBadge",
        "type": "styleguide"
      },
      "styles": {}
    }
  ],
  "theme": {
    "bold": 700,
    "breakpoints": [
      "@media screen and (min-width:32em)",
      "@media screen and (min-width:48em)",
      "@media screen and (min-width:64em)",
      "@media screen and (min-width:96em)"
    ],
    "fontFamily": "\"Helvetica Neue\", Helvetica, Arial, sans-serif",
    "h1": {
      "fontSize": [
        5,
        null,
        6,
        null,
        6
      ],
      "fontWeight": 700,
      "lineHeight": 1.125
    },
    "h2": {
      "fontSize": [
        3,
        null,
        3,
        null,
        3
      ],
      "fontWeight": 700,
      "letterSpacing": 0.125,
      "lineHeight": 1.125,
      "textTransform": "uppercase"
    },
    "h3": {
      "fontSize": [
        2,
        null,
        3
      ],
      "fontWeight": 700,
      "lineHeight": 1.125
    },
    "lineHeight": 1.5,
    "links": [
      {
        "color": 1,
        "hover": {
          "color": 3,
          "textDecoration": "underline"
        },
        "textDecoration": "none"
      },
      {
        ":hover": {
          "color": 3
        },
        "color": 3,
        "display": "inline-block",
        "fontWeight": 700,
        "paddingBottom": 2,
        "paddingTop": 2,
        "textDecoration": "none"
      },
      {
        "backgroundColor": 3,
        "border": 0,
        "borderColor": null,
        "borderRadius": 0,
        "color": 0,
        "display": "inline-block",
        "fontWeight": 700,
        "hover": {
          "backgroundColor": null,
          "borderColor": null,
          "color": "white"
        },
        "paddingBottom": 2,
        "paddingLeft": 24,
        "paddingRight": 24,
        "paddingTop": 2,
        "textAlign": "center",
        "textDecoration": "none",
        "whiteSpace": "nowrap"
      },
      {
        ":hover": {
          "color": ""
        },
        "backgroundColor": "white",
        "border": 0,
        "borderColor": null,
        "borderRadius": 0,
        "color": 0,
        "display": "inline-block",
        "fontWeight": 700,
        "hover": {
          "backgroundColor": null,
          "borderColor": null,
          "color": "white"
        },
        "paddingBottom": 2,
        "paddingLeft": 24,
        "paddingRight": 24,
        "paddingTop": 2,
        "textAlign": "center",
        "textDecoration": "none",
        "whiteSpace": "nowrap"
      },
      {
        "backgroundColor": 0,
        "border": 0,
        "borderColor": null,
        "borderRadius": 0,
        "color": "white",
        "display": "inline-block",
        "fontWeight": 700,
        "hover": {
          "backgroundColor": null,
          "borderColor": null,
          "color": "white"
        },
        "paddingBottom": 2,
        "paddingLeft": 24,
        "paddingRight": 24,
        "paddingTop": 2,
        "textAlign": "center",
        "textDecoration": "none",
        "whiteSpace": "nowrap"
      }
    ],
    "maxWidth": 1024,
    "name": "Custom",
    "palette": [
      "#222",
      "#09a",
      "#444",
      "tomato",
      "#ccc",
      "#eee",
      "#111"
    ],
    "radius": 2,
    "space": [
      0,
      4,
      8,
      16,
      32,
      64,
      128,
      256,
      512
    ],
    "typeScale": [
      12,
      14,
      16,
      20,
      24,
      32,
      48,
      64,
      96,
      128
    ],
    "white": "#fff"
  }
}